__init__.py
detti_conf.ini
detti_db.py
detti_server.py
detti_db_server-1.2.1.data/scripts/color_logger.py
doc/pics/detti_db_logo.png
tools/color_logger.py
detti_db_server-1.2.1.dist-info/LICENSE
detti_db_server-1.2.1.dist-info/METADATA
detti_db_server-1.2.1.dist-info/WHEEL
detti_db_server-1.2.1.dist-info/top_level.txt
detti_db_server-1.2.1.dist-info/RECORD
