Metadata-Version: 2.1
Name: detti-db-server
Version: 1.2.1
Summary: Lightweight Json based key-value DB and/or server.
Home-page: https://github.com/milanbalazs/detti_db_server
Author: Milan Balazs
Author-email: milanbalazs01@gmail.com
License: three-clause BSD
Platform: UNKNOWN
Classifier: Programming Language :: Python
Classifier: Programming Language :: Python :: 3
Classifier: Programming Language :: Python :: 3.6
Classifier: Programming Language :: Python :: Implementation :: CPython
Classifier: Programming Language :: Python :: Implementation :: PyPy
Classifier: License :: OSI Approved :: BSD License
Classifier: Intended Audience :: Developers
Classifier: Topic :: Database
Classifier: Operating System :: POSIX
Classifier: Operating System :: Unix
Classifier: Typing :: Typed
Classifier: Natural Language :: English
Classifier: Framework :: Flask
Requires-Python: >=3.6
Requires-Dist: Flask-Limiter (==1.4)
Requires-Dist: Flask-RESTful (==0.3.8)
Requires-Dist: Werkzeug (==1.0.1)
Requires-Dist: coverage (==5.4)
Requires-Dist: pycodestyle (==2.6.0)
Requires-Dist: requests (==2.25.1)
Requires-Dist: Flask-JWT (==0.3.2)
Requires-Dist: pre-commit (==2.11.0)
Requires-Dist: Flask-Cors (==3.0.10)
